{
  "mappings" : [ {
    "id" : "5c9a2b9a-af57-4f45-8ac6-0e0e1fdd2f3f",
    "name" : "Project Details - 200",
    "request" : {
      "urlPath" : "/project/2012706729690494359.json",
      "method" : "GET",
      "queryParameters" : {
        "api_key" : {
          "equalTo" : "7jx1tlboa4yl6tlwaf6sn5igxky126b0psao37y8lczbg9ottlxbhfr25qyp4ew9eak0mkuq4tfe02c5ewzsaz71k3u"
        }
      }
    },
    "response" : {
      "status" : 200
    },
    "uuid" : "5c9a2b9a-af57-4f45-8ac6-0e0e1fdd2f3f",
    "persistent" : true,
    "metadata" : {
      "mocklab" : {
        "created" : {
          "at" : "2023-03-06T18:55:42.850899Z",
          "via" : "OAS3_IMPORT"
        },
        "oas" : {
          "operationId" : "document"
        }
      }
    }
  }, {
    "id" : "ee5d4b19-1e3a-4852-a6b3-788e5472d007",
    "name" : "A filterable list of projects. - 200",
    "request" : {
      "urlPath" : "/project.xml",
      "method" : "GET",
      "queryParameters" : {
        "api_key" : {
          "equalTo" : "779ecue8vt9obyl4f6jimx988"
        }
      }
    },
    "response" : {
      "status" : 200
    },
    "uuid" : "ee5d4b19-1e3a-4852-a6b3-788e5472d007",
    "persistent" : true,
    "metadata" : {
      "mocklab" : {
        "created" : {
          "at" : "2023-03-06T18:55:42.850798Z",
          "via" : "OAS3_IMPORT"
        },
        "oas" : {
          "operationId" : "project"
        }
      }
    }
  } ]
}